pseudopeople/__about__.py
pseudopeople/__init__.py
pseudopeople/_version.py
pseudopeople/column_getters.py
pseudopeople/dtypes.py
pseudopeople/entity_types.py
pseudopeople/exceptions.py
pseudopeople/interface.py
pseudopeople/loader.py
pseudopeople/noise.py
pseudopeople/noise_entities.py
pseudopeople/noise_functions.py
pseudopeople/noise_scaling.py
pseudopeople/output_dtype_getters.py
pseudopeople/schema_entities.py
pseudopeople/utilities.py
pseudopeople/configuration/__init__.py
pseudopeople/configuration/entities.py
pseudopeople/configuration/generator.py
pseudopeople/configuration/interface.py
pseudopeople/configuration/validator.py
pseudopeople/constants/data_values.py
pseudopeople/constants/metadata.py
pseudopeople/constants/noise_type_metadata.py
pseudopeople/constants/paths.py
pseudopeople/data/fake_names.py
pseudopeople/data/incorrect_select_options.csv
pseudopeople/data/nicknames.csv
pseudopeople/data/ocr_errors.csv
pseudopeople/data/phonetic_variations.csv
pseudopeople/data/qwerty_errors.yaml
pseudopeople/data/sample_datasets/metadata_proportions.csv
pseudopeople/data/sample_datasets/american_community_survey/american_community_survey.parquet
pseudopeople/data/sample_datasets/current_population_survey/current_population_survey.parquet
pseudopeople/data/sample_datasets/decennial_census/decennial_census.parquet
pseudopeople/data/sample_datasets/social_security/social_security.parquet
pseudopeople/data/sample_datasets/taxes_1040/taxes_1040.parquet
pseudopeople/data/sample_datasets/taxes_w2_and_1099/taxes_w2_and_1099.parquet
pseudopeople/data/sample_datasets/women_infants_and_children/women_infants_and_children.parquet
pseudopeople-1.2.7.dist-info/licenses/LICENSE
pseudopeople-1.2.7.dist-info/METADATA
pseudopeople-1.2.7.dist-info/WHEEL
pseudopeople-1.2.7.dist-info/top_level.txt
pseudopeople-1.2.7.dist-info/RECORD
